{"0":[{"turn":1,"player":"a","type":"fast","arg":null,"priority":20},{"turn":1,"player":"b","type":"fast","arg":null,"priority":20},{"turn":2,"player":"b","type":"fast","arg":null,"priority":20},{"turn":3,"player":"b","type":"switch","arg":1,"priority":0},{"turn":2,"player":"a","type":"fast","arg":null,"priority":20},{"turn":3,"player":"a","type":"fast","arg":null,"priority":20},{"turn":4,"player":"b","type":"fast","arg":null,"priority":20},{"turn":4,"player":"a","type":"fast","arg":null,"priority":20},{"turn":5,"player":"b","type":"fast","arg":null,"priority":20},{"turn":5,"player":"a","type":"fast","arg":null,"priority":20},{"turn":6,"player":"b","type":"fast","arg":null,"priority":20},{"turn":6,"player":"a","type":"fast","arg":null,"priority":20},{"turn":7,"player":"b","type":"fast","arg":null,"priority":20},{"turn":7,"player":"a","type":"fast","arg":null,"priority":20},{"turn":8,"player":"b","type":"fast","arg":null,"priority":20},{"turn":9,"player":"b","type":"fast","arg":null,"priority":20},{"turn":8,"player":"a","type":"switch","arg":1,"priority":0},{"turn":10,"player":"b","type":"fast","arg":null,"priority":-20},{"turn":11,"player":"a","type":"fast","arg":null,"priority":-20},{"turn":12,"player":"b","type":"fast","arg":null,"priority":20},{"turn":11,"player":"b","type":"charged","arg":"b","priority":0},{"turn":12,"player":"a","type":"fast","arg":null,"priority":20},{"turn":13,"player":"b","type":"fast","arg":null,"priority":20},{"turn":13,"player":"a","type":"fast","arg":null,"priority":20},{"turn":14,"player":"b","type":"fast","arg":null,"priority":20},{"turn":14,"player":"a","type":"fast","arg":null,"priority":20},{"turn":15,"player":"b","type":"fast","arg":null,"priority":20},{"turn":15,"player":"a","type":"fast","arg":null,"priority":20},{"turn":16,"player":"b","type":"fast","arg":null,"priority":20},{"turn":16,"player":"a","type":"fast","arg":null,"priority":20},{"turn":17,"player":"b","type":"fast","arg":null,"priority":20},{"turn":17,"player":"a","type":"fast","arg":null,"priority":20},{"turn":18,"player":"b","type":"fast","arg":null,"priority":20},{"turn":18,"player":"a","type":"fast","arg":null,"priority":20},{"turn":19,"player":"b","type":"fast","arg":null,"priority":20},{"turn":20,"player":"b","type":"charged","arg":"b","priority":0},{"turn":19,"player":"a","type":"fast","arg":null,"priority":20},{"turn":21,"player":"a","type":"charged","arg":"b","priority":0},{"turn":20,"player":"a","type":"fast","arg":null,"priority":20},{"turn":21,"player":"b","type":"fast","arg":null,"priority":20},{"turn":22,"player":"b","type":"fast","arg":null,"priority":20},{"turn":22,"player":"a","type":"fast","arg":null,"priority":20},{"turn":23,"player":"b","type":"fast","arg":null,"priority":20},{"turn":23,"player":"a","type":"fast","arg":null,"priority":20},{"turn":24,"player":"b","type":"fast","arg":null,"priority":20},{"turn":24,"player":"a","type":"fast","arg":null,"priority":20},{"turn":25,"player":"b","type":"fast","arg":null,"priority":20},{"turn":25,"player":"a","type":"fast","arg":null,"priority":20},{"turn":26,"player":"b","type":"fast","arg":null,"priority":20},{"turn":27,"player":"b","type":"fast","arg":null,"priority":-20},{"turn":26,"player":"a","type":"fast","arg":null,"priority":20},{"turn":28,"player":"a","type":"fast","arg":null,"priority":-20},{"turn":27,"player":"a","type":"charged","arg":"b","priority":0},{"turn":28,"player":"b","type":"charged","arg":"b","priority":0},{"turn":30,"player":"a","type":"fast","arg":null,"priority":-20},{"turn":31,"player":"b","type":"fast","arg":null,"priority":20},{"turn":31,"player":"a","type":"fast","arg":null,"priority":20},{"turn":32,"player":"b","type":"fast","arg":null,"priority":20},{"turn":32,"player":"a","type":"fast","arg":null,"priority":20},{"turn":33,"player":"b","type":"fast","arg":null,"priority":20},{"turn":33,"player":"a","type":"fast","arg":null,"priority":20},{"turn":34,"player":"b","type":"fast","arg":null,"priority":20},{"turn":35,"player":"b","type":"fast","arg":null,"priority":-20},{"turn":34,"player":"a","type":"fast","arg":null,"priority":20},{"turn":36,"player":"b","type":"fast","arg":null,"priority":20},{"turn":35,"player":"a","type":"charged","arg":"b","priority":0},{"turn":36,"player":"a","type":"fast","arg":null,"priority":20},{"turn":37,"player":"b","type":"fast","arg":null,"priority":20},{"turn":37,"player":"a","type":"fast","arg":null,"priority":20},{"turn":38,"player":"b","type":"fast","arg":null,"priority":20},{"turn":38,"player":"a","type":"fast","arg":null,"priority":20},{"turn":39,"player":"b","type":"fast","arg":null,"priority":20},{"turn":39,"player":"a","type":"fast","arg":null,"priority":20},{"turn":40,"player":"b","type":"fast","arg":null,"priority":20},{"turn":40,"player":"a","type":"fast","arg":null,"priority":20},{"turn":41,"player":"b","type":"fast","arg":null,"priority":20},{"turn":42,"player":"b","type":"charged","arg":"a","priority":0},{"turn":41,"player":"a","type":"fast","arg":null,"priority":20},{"turn":42,"player":"a","type":"fast","arg":null,"priority":20},{"turn":43,"player":"b","type":"fast","arg":null,"priority":20},{"turn":44,"player":"b","type":"fast","arg":null,"priority":-20},{"turn":43,"player":"a","type":"fast","arg":null,"priority":20},{"turn":45,"player":"b","type":"fast","arg":null,"priority":20},{"turn":44,"player":"a","type":"charged","arg":"b","priority":0},{"turn":46,"player":"b","type":"fast","arg":null,"priority":-20},{"turn":45,"player":"a","type":"fast","arg":null,"priority":20},{"turn":47,"player":"b","type":"fast","arg":null,"priority":20},{"turn":47,"player":"a","type":"fast","arg":null,"priority":20},{"turn":48,"player":"b","type":"fast","arg":null,"priority":20},{"turn":48,"player":"a","type":"fast","arg":null,"priority":20},{"turn":49,"player":"b","type":"fast","arg":null,"priority":20},{"turn":50,"player":"b","type":"charged","arg":"a","priority":0},{"turn":49,"player":"a","type":"fast","arg":null,"priority":20},{"turn":50,"player":"a","type":"fast","arg":null,"priority":20},{"turn":51,"player":"b","type":"fast","arg":null,"priority":20},{"turn":52,"player":"b","type":"fast","arg":null,"priority":-20},{"turn":51,"player":"a","type":"fast","arg":null,"priority":20},{"turn":53,"player":"a","type":"charged","arg":"b","priority":0},{"turn":53,"player":"b","type":"fast","arg":null,"priority":20},{"turn":54,"player":"b","type":"fast","arg":null,"priority":20},{"turn":54,"player":"a","type":"fast","arg":null,"priority":20},{"turn":55,"player":"b","type":"fast","arg":null,"priority":20},{"turn":55,"player":"a","type":"fast","arg":null,"priority":20},{"turn":56,"player":"b","type":"fast","arg":null,"priority":20},{"turn":56,"player":"a","type":"fast","arg":null,"priority":20},{"turn":57,"player":"b","type":"fast","arg":null,"priority":20},{"turn":57,"player":"a","type":"fast","arg":null,"priority":20},{"turn":58,"player":"b","type":"fast","arg":null,"priority":20},{"turn":58,"player":"a","type":"fast","arg":null,"priority":20},{"turn":59,"player":"b","type":"fast","arg":null,"priority":20},{"turn":59,"player":"a","type":"fast","arg":null,"priority":20},{"turn":61,"player":"b","type":"fast","arg":null,"priority":20},{"turn":60,"player":"a","type":"charged","arg":"b","priority":0},{"turn":61,"player":"a","type":"fast","arg":null,"priority":20},{"turn":62,"player":"b","type":"fast","arg":null,"priority":20},{"turn":63,"player":"b","type":"charged","arg":"b","priority":0},{"turn":62,"player":"a","type":"fast","arg":null,"priority":20},{"turn":63,"player":"a","type":"fast","arg":null,"priority":20},{"turn":64,"player":"b","type":"fast","arg":null,"priority":20},{"turn":65,"player":"b","type":"fast","arg":null,"priority":-20},{"turn":64,"player":"a","type":"fast","arg":null,"priority":20},{"turn":66,"player":"a","type":"fast","arg":null,"priority":-20},{"turn":65,"player":"a","type":"charged","arg":"b","priority":0},{"turn":66,"player":"b","type":"charged","arg":"a","priority":0},{"turn":68,"player":"a","type":"fast","arg":null,"priority":-20},{"turn":69,"player":"b","type":"fast","arg":null,"priority":20},{"turn":69,"player":"a","type":"fast","arg":null,"priority":20},{"turn":70,"player":"b","type":"fast","arg":null,"priority":20},{"turn":70,"player":"a","type":"fast","arg":null,"priority":20},{"turn":71,"player":"b","type":"fast","arg":null,"priority":20},{"turn":72,"player":"b","type":"fast","arg":null,"priority":-20},{"turn":71,"player":"a","type":"fast","arg":null,"priority":20},{"turn":73,"player":"a","type":"charged","arg":"b","priority":0}],"1":[{"turn":1,"player":"a","type":"switch","arg":2,"priority":0},{"turn":1,"player":"b","type":"fast","arg":null,"priority":20},{"turn":2,"player":"b","type":"fast","arg":null,"priority":20},{"turn":3,"player":"b","type":"switch","arg":1,"priority":0},{"turn":2,"player":"a","type":"fast","arg":null,"priority":20},{"turn":4,"player":"b","type":"fast","arg":null,"priority":20},{"turn":3,"player":"a","type":"fast","arg":null,"priority":20},{"turn":5,"player":"b","type":"fast","arg":null,"priority":20},{"turn":4,"player":"a","type":"fast","arg":null,"priority":20},{"turn":6,"player":"b","type":"fast","arg":null,"priority":20},{"turn":5,"player":"a","type":"fast","arg":null,"priority":20},{"turn":7,"player":"b","type":"fast","arg":null,"priority":20},{"turn":6,"player":"a","type":"fast","arg":null,"priority":20},{"turn":8,"player":"b","type":"fast","arg":null,"priority":20},{"turn":7,"player":"a","type":"fast","arg":null,"priority":20},{"turn":9,"player":"a","type":"charged","arg":"a","priority":0},{"turn":8,"player":"a","type":"fast","arg":null,"priority":20},{"turn":10,"player":"b","type":"fast","arg":null,"priority":20},{"turn":9,"player":"b","type":"fast","arg":null,"priority":20},{"turn":11,"player":"b","type":"fast","arg":null,"priority":20},{"turn":10,"player":"a","type":"fast","arg":null,"priority":20},{"turn":12,"player":"b","type":"fast","arg":null,"priority":20},{"turn":11,"player":"a","type":"fast","arg":null,"priority":20},{"turn":13,"player":"b","type":"fast","arg":null,"priority":20},{"turn":12,"player":"a","type":"fast","arg":null,"priority":20},{"turn":14,"player":"b","type":"fast","arg":null,"priority":20},{"turn":13,"player":"a","type":"fast","arg":null,"priority":20},{"turn":15,"player":"a","type":"charged","arg":"a","priority":0},{"turn":14,"player":"a","type":"fast","arg":null,"priority":20},{"turn":16,"player":"b","type":"fast","arg":null,"priority":20},{"turn":15,"player":"b","type":"fast","arg":null,"priority":20},{"turn":17,"player":"b","type":"fast","arg":null,"priority":20},{"turn":16,"player":"a","type":"fast","arg":null,"priority":20},{"turn":18,"player":"b","type":"fast","arg":null,"priority":20},{"turn":17,"player":"a","type":"fast","arg":null,"priority":20},{"turn":19,"player":"b","type":"fast","arg":null,"priority":20},{"turn":18,"player":"a","type":"fast","arg":null,"priority":20},{"turn":20,"player":"b","type":"fast","arg":null,"priority":20},{"turn":19,"player":"a","type":"fast","arg":null,"priority":20},{"turn":21,"player":"a","type":"charged","arg":"a","priority":0},{"turn":20,"player":"a","type":"fast","arg":null,"priority":20},{"turn":22,"player":"b","type":"fast","arg":null,"priority":20},{"turn":21,"player":"b","type":"fast","arg":null,"priority":20},{"turn":23,"player":"b","type":"fast","arg":null,"priority":20},{"turn":22,"player":"a","type":"fast","arg":null,"priority":20},{"turn":23,"player":"a","type":"fast","arg":null,"priority":20},{"turn":25,"player":"b","type":"fast","arg":null,"priority":20},{"turn":25,"player":"a","type":"fast","arg":null,"priority":20},{"turn":26,"player":"b","type":"fast","arg":null,"priority":20},{"turn":26,"player":"a","type":"fast","arg":null,"priority":20},{"turn":27,"player":"b","type":"fast","arg":null,"priority":20},{"turn":28,"player":"b","type":"fast","arg":null,"priority":-20},{"turn":27,"player":"a","type":"fast","arg":null,"priority":20},{"turn":29,"player":"a","type":"charged","arg":"a","priority":0},{"turn":29,"player":"b","type":"fast","arg":null,"priority":20},{"turn":30,"player":"b","type":"fast","arg":null,"priority":20},{"turn":30,"player":"a","type":"fast","arg":null,"priority":20},{"turn":31,"player":"b","type":"fast","arg":null,"priority":20},{"turn":31,"player":"a","type":"fast","arg":null,"priority":20},{"turn":32,"player":"b","type":"fast","arg":null,"priority":20},{"turn":33,"player":"b","type":"charged","arg":"a","priority":0},{"turn":32,"player":"a","type":"fast","arg":null,"priority":20},{"turn":33,"player":"a","type":"fast","arg":null,"priority":20},{"turn":34,"player":"b","type":"fast","arg":null,"priority":20},{"turn":35,"player":"b","type":"fast","arg":null,"priority":-20},{"turn":34,"player":"a","type":"fast","arg":null,"priority":20},{"turn":36,"player":"a","type":"charged","arg":"a","priority":0},{"turn":36,"player":"b","type":"fast","arg":null,"priority":20},{"turn":37,"player":"b","type":"fast","arg":null,"priority":20},{"turn":37,"player":"a","type":"fast","arg":null,"priority":20},{"turn":38,"player":"b","type":"fast","arg":null,"priority":20},{"turn":38,"player":"a","type":"fast","arg":null,"priority":20},{"turn":39,"player":"b","type":"fast","arg":null,"priority":20},{"turn":39,"player":"a","type":"fast","arg":null,"priority":20},{"turn":40,"player":"b","type":"fast","arg":null,"priority":20},{"turn":40,"player":"a","type":"fast","arg":null,"priority":20},{"turn":41,"player":"b","type":"fast","arg":null,"priority":20},{"turn":42,"player":"b","type":"fast","arg":null,"priority":-20},{"turn":41,"player":"a","type":"fast","arg":null,"priority":20},{"turn":43,"player":"a","type":"charged","arg":"a","priority":0},{"turn":43,"player":"b","type":"fast","arg":null,"priority":20},{"turn":44,"player":"b","type":"fast","arg":null,"priority":20},{"turn":44,"player":"a","type":"fast","arg":null,"priority":20},{"turn":45,"player":"b","type":"fast","arg":null,"priority":20},{"turn":45,"player":"a","type":"fast","arg":null,"priority":20},{"turn":46,"player":"b","type":"fast","arg":null,"priority":20},{"turn":46,"player":"a","type":"fast","arg":null,"priority":20},{"turn":47,"player":"b","type":"fast","arg":null,"priority":20},{"turn":47,"player":"a","type":"fast","arg":null,"priority":20}],"2":[{"turn":1,"player":"b","type":"fast","arg":null,"priority":20},{"turn":1,"player":"a","type":"fast","arg":null,"priority":20},{"turn":2,"player":"b","type":"fast","arg":null,"priority":20},{"turn":2,"player":"a","type":"fast","arg":null,"priority":20},{"turn":3,"player":"b","type":"fast","arg":null,"priority":20},{"turn":3,"player":"a","type":"fast","arg":null,"priority":20},{"turn":4,"player":"b","type":"fast","arg":null,"priority":20},{"turn":4,"player":"a","type":"fast","arg":null,"priority":20},{"turn":5,"player":"b","type":"fast","arg":null,"priority":20},{"turn":5,"player":"a","type":"fast","arg":null,"priority":20},{"turn":6,"player":"b","type":"fast","arg":null,"priority":20},{"turn":6,"player":"a","type":"fast","arg":null,"priority":20},{"turn":7,"player":"b","type":"switch","arg":1,"priority":0},{"turn":7,"player":"a","type":"fast","arg":null,"priority":20},{"turn":8,"player":"a","type":"fast","arg":null,"priority":20},{"turn":9,"player":"a","type":"charged","arg":"b","priority":0},{"turn":8,"player":"b","type":"fast","arg":null,"priority":20},{"turn":9,"player":"b","type":"fast","arg":null,"priority":20},{"turn":10,"player":"a","type":"fast","arg":null,"priority":20},{"turn":11,"player":"a","type":"fast","arg":null,"priority":20},{"turn":10,"player":"b","type":"fast","arg":null,"priority":20},{"turn":12,"player":"a","type":"fast","arg":null,"priority":20},{"turn":11,"player":"b","type":"fast","arg":null,"priority":20},{"turn":13,"player":"a","type":"fast","arg":null,"priority":20},{"turn":12,"player":"b","type":"fast","arg":null,"priority":20},{"turn":14,"player":"a","type":"fast","arg":null,"priority":20},{"turn":13,"player":"b","type":"fast","arg":null,"priority":20},{"turn":15,"player":"a","type":"fast","arg":null,"priority":20},{"turn":14,"player":"b","type":"fast","arg":null,"priority":20},{"turn":16,"player":"a","type":"fast","arg":null,"priority":20},{"turn":17,"player":"a","type":"charged","arg":"a","priority":0},{"turn":15,"player":"b","type":"fast","arg":null,"priority":20},{"turn":17,"player":"b","type":"charged","arg":"b","priority":0},{"turn":16,"player":"b","type":"fast","arg":null,"priority":20},{"turn":18,"player":"a","type":"fast","arg":null,"priority":20},{"turn":19,"player":"a","type":"fast","arg":null,"priority":20},{"turn":20,"player":"a","type":"switch","arg":1,"priority":0},{"turn":18,"player":"b","type":"fast","arg":null,"priority":20},{"turn":21,"player":"b","type":"charged","arg":"b","priority":0},{"turn":20,"player":"b","type":"fast","arg":null,"priority":-20},{"turn":19,"player":"b","type":"fast","arg":null,"priority":20},{"turn":21,"player":"a","type":"fast","arg":null,"priority":20},{"turn":22,"player":"a","type":"fast","arg":null,"priority":20},{"turn":23,"player":"a","type":"fast","arg":null,"priority":20},{"turn":22,"player":"b","type":"fast","arg":null,"priority":20},{"turn":24,"player":"a","type":"fast","arg":null,"priority":20},{"turn":23,"player":"b","type":"fast","arg":null,"priority":20},{"turn":25,"player":"a","type":"fast","arg":null,"priority":20},{"turn":24,"player":"b","type":"fast","arg":null,"priority":20},{"turn":26,"player":"a","type":"fast","arg":null,"priority":20},{"turn":25,"player":"b","type":"fast","arg":null,"priority":20},{"turn":27,"player":"a","type":"fast","arg":null,"priority":20},{"turn":26,"player":"b","type":"fast","arg":null,"priority":20},{"turn":28,"player":"a","type":"fast","arg":null,"priority":20},{"turn":27,"player":"b","type":"fast","arg":null,"priority":20},{"turn":29,"player":"a","type":"fast","arg":null,"priority":20},{"turn":28,"player":"b","type":"fast","arg":null,"priority":20},{"turn":30,"player":"a","type":"fast","arg":null,"priority":20},{"turn":29,"player":"b","type":"fast","arg":null,"priority":20},{"turn":31,"player":"a","type":"fast","arg":null,"priority":20},{"turn":32,"player":"a","type":"fast","arg":null,"priority":-20},{"turn":30,"player":"b","type":"fast","arg":null,"priority":20},{"turn":32,"player":"b","type":"charged","arg":"a","priority":0},{"turn":33,"player":"b","type":"fast","arg":null,"priority":-20},{"turn":31,"player":"b","type":"fast","arg":null,"priority":20},{"turn":34,"player":"a","type":"charged","arg":"b","priority":0},{"turn":35,"player":"a","type":"fast","arg":null,"priority":-20},{"turn":34,"player":"b","type":"charged","arg":"a","priority":0},{"turn":36,"player":"a","type":"fast","arg":null,"priority":-20},{"turn":37,"player":"b","type":"fast","arg":null,"priority":20},{"turn":37,"player":"a","type":"fast","arg":null,"priority":20},{"turn":38,"player":"b","type":"fast","arg":null,"priority":20},{"turn":38,"player":"a","type":"fast","arg":null,"priority":20},{"turn":39,"player":"b","type":"fast","arg":null,"priority":20},{"turn":39,"player":"a","type":"fast","arg":null,"priority":20},{"turn":40,"player":"b","type":"fast","arg":null,"priority":20},{"turn":40,"player":"a","type":"fast","arg":null,"priority":20},{"turn":41,"player":"b","type":"fast","arg":null,"priority":20},{"turn":42,"player":"b","type":"charged","arg":"a","priority":0},{"turn":41,"player":"a","type":"fast","arg":null,"priority":20},{"turn":42,"player":"a","type":"fast","arg":null,"priority":20},{"turn":43,"player":"b","type":"fast","arg":null,"priority":20},{"turn":43,"player":"a","type":"fast","arg":null,"priority":20},{"turn":44,"player":"a","type":"fast","arg":null,"priority":20},{"turn":45,"player":"b","type":"fast","arg":null,"priority":20},{"turn":46,"player":"b","type":"fast","arg":null,"priority":20},{"turn":45,"player":"a","type":"fast","arg":null,"priority":20},{"turn":47,"player":"b","type":"fast","arg":null,"priority":20},{"turn":46,"player":"a","type":"fast","arg":null,"priority":20},{"turn":48,"player":"b","type":"fast","arg":null,"priority":20},{"turn":47,"player":"a","type":"fast","arg":null,"priority":20},{"turn":49,"player":"b","type":"fast","arg":null,"priority":20},{"turn":48,"player":"a","type":"fast","arg":null,"priority":20},{"turn":50,"player":"b","type":"fast","arg":null,"priority":20},{"turn":49,"player":"a","type":"fast","arg":null,"priority":20},{"turn":51,"player":"b","type":"fast","arg":null,"priority":20},{"turn":50,"player":"a","type":"fast","arg":null,"priority":20},{"turn":52,"player":"a","type":"charged","arg":"a","priority":0},{"turn":51,"player":"a","type":"fast","arg":null,"priority":20}],"3":[{"turn":1,"player":"a","type":"fast","arg":null,"priority":20},{"turn":1,"player":"b","type":"fast","arg":null,"priority":20},{"turn":3,"player":"a","type":"switch","arg":1,"priority":0},{"turn":2,"player":"a","type":"fast","arg":null,"priority":20},{"turn":2,"player":"b","type":"fast","arg":null,"priority":20},{"turn":4,"player":"a","type":"fast","arg":null,"priority":20},{"turn":3,"player":"b","type":"fast","arg":null,"priority":20},{"turn":5,"player":"a","type":"fast","arg":null,"priority":20},{"turn":4,"player":"b","type":"fast","arg":null,"priority":20},{"turn":6,"player":"a","type":"fast","arg":null,"priority":20},{"turn":5,"player":"b","type":"fast","arg":null,"priority":20},{"turn":7,"player":"a","type":"fast","arg":null,"priority":20},{"turn":6,"player":"b","type":"fast","arg":null,"priority":20},{"turn":8,"player":"a","type":"fast","arg":null,"priority":20},{"turn":7,"player":"b","type":"fast","arg":null,"priority":20},{"turn":9,"player":"a","type":"fast","arg":null,"priority":20},{"turn":8,"player":"b","type":"fast","arg":null,"priority":20},{"turn":10,"player":"a","type":"fast","arg":null,"priority":20},{"turn":9,"player":"b","type":"fast","arg":null,"priority":20},{"turn":11,"player":"a","type":"fast","arg":null,"priority":20},{"turn":10,"player":"b","type":"fast","arg":null,"priority":20},{"turn":12,"player":"a","type":"fast","arg":null,"priority":20},{"turn":13,"player":"a","type":"charged","arg":"b","priority":0},{"turn":11,"player":"b","type":"fast","arg":null,"priority":20},{"turn":13,"player":"b","type":"switch","arg":1,"priority":0},{"turn":12,"player":"b","type":"fast","arg":null,"priority":20},{"turn":14,"player":"b","type":"fast","arg":null,"priority":20},{"turn":15,"player":"b","type":"fast","arg":null,"priority":20},{"turn":14,"player":"a","type":"fast","arg":null,"priority":20},{"turn":16,"player":"b","type":"fast","arg":null,"priority":20},{"turn":15,"player":"a","type":"fast","arg":null,"priority":20},{"turn":17,"player":"b","type":"fast","arg":null,"priority":20},{"turn":16,"player":"a","type":"fast","arg":null,"priority":20},{"turn":18,"player":"b","type":"fast","arg":null,"priority":20},{"turn":17,"player":"a","type":"fast","arg":null,"priority":20},{"turn":19,"player":"b","type":"fast","arg":null,"priority":20},{"turn":18,"player":"a","type":"fast","arg":null,"priority":20},{"turn":20,"player":"b","type":"fast","arg":null,"priority":20},{"turn":19,"player":"a","type":"fast","arg":null,"priority":20},{"turn":21,"player":"b","type":"fast","arg":null,"priority":20},{"turn":20,"player":"a","type":"fast","arg":null,"priority":20},{"turn":22,"player":"b","type":"fast","arg":null,"priority":20},{"turn":21,"player":"a","type":"fast","arg":null,"priority":20},{"turn":23,"player":"b","type":"fast","arg":null,"priority":20},{"turn":22,"player":"a","type":"fast","arg":null,"priority":20},{"turn":24,"player":"b","type":"fast","arg":null,"priority":20},{"turn":23,"player":"a","type":"fast","arg":null,"priority":20},{"turn":25,"player":"a","type":"charged","arg":"a","priority":0},{"turn":24,"player":"a","type":"fast","arg":null,"priority":20},{"turn":26,"player":"b","type":"fast","arg":null,"priority":20},{"turn":25,"player":"b","type":"fast","arg":null,"priority":20},{"turn":27,"player":"b","type":"fast","arg":null,"priority":20},{"turn":26,"player":"a","type":"fast","arg":null,"priority":20},{"turn":28,"player":"a","type":"fast","arg":null,"priority":-20},{"turn":27,"player":"a","type":"fast","arg":null,"priority":20},{"turn":29,"player":"b","type":"fast","arg":null,"priority":20},{"turn":28,"player":"b","type":"charged","arg":"b","priority":0},{"turn":29,"player":"a","type":"fast","arg":null,"priority":20},{"turn":31,"player":"b","type":"fast","arg":null,"priority":20},{"turn":32,"player":"b","type":"fast","arg":null,"priority":20},{"turn":31,"player":"a","type":"fast","arg":null,"priority":20},{"turn":33,"player":"b","type":"fast","arg":null,"priority":20},{"turn":32,"player":"a","type":"fast","arg":null,"priority":20},{"turn":34,"player":"b","type":"fast","arg":null,"priority":20},{"turn":33,"player":"a","type":"fast","arg":null,"priority":20},{"turn":35,"player":"b","type":"fast","arg":null,"priority":20},{"turn":34,"player":"a","type":"fast","arg":null,"priority":20},{"turn":36,"player":"b","type":"fast","arg":null,"priority":20},{"turn":35,"player":"a","type":"fast","arg":null,"priority":20},{"turn":37,"player":"a","type":"charged","arg":"a","priority":0},{"turn":36,"player":"a","type":"fast","arg":null,"priority":20},{"turn":38,"player":"b","type":"fast","arg":null,"priority":20},{"turn":37,"player":"b","type":"fast","arg":null,"priority":20},{"turn":39,"player":"b","type":"fast","arg":null,"priority":20},{"turn":38,"player":"a","type":"fast","arg":null,"priority":20},{"turn":40,"player":"b","type":"fast","arg":null,"priority":20},{"turn":39,"player":"a","type":"fast","arg":null,"priority":20},{"turn":40,"player":"a","type":"fast","arg":null,"priority":20},{"turn":42,"player":"b","type":"fast","arg":null,"priority":20},{"turn":41,"player":"a","type":"fast","arg":null,"priority":20},{"turn":43,"player":"b","type":"fast","arg":null,"priority":20},{"turn":42,"player":"a","type":"fast","arg":null,"priority":20},{"turn":44,"player":"a","type":"charged","arg":"a","priority":0},{"turn":43,"player":"a","type":"fast","arg":null,"priority":20},{"turn":45,"player":"a","type":"fast","arg":null,"priority":-20},{"turn":44,"player":"b","type":"fast","arg":null,"priority":20},{"turn":46,"player":"a","type":"fast","arg":null,"priority":-20},{"turn":45,"player":"b","type":"charged","arg":"a","priority":0},{"turn":48,"player":"a","type":"charged","arg":"a","priority":0},{"turn":48,"player":"b","type":"fast","arg":null,"priority":20},{"turn":49,"player":"a","type":"fast","arg":null,"priority":20},{"turn":49,"player":"b","type":"fast","arg":null,"priority":20},{"turn":50,"player":"b","type":"fast","arg":null,"priority":20},{"turn":50,"player":"a","type":"fast","arg":null,"priority":20},{"turn":51,"player":"b","type":"fast","arg":null,"priority":20},{"turn":51,"player":"a","type":"fast","arg":null,"priority":20},{"turn":52,"player":"b","type":"fast","arg":null,"priority":20},{"turn":52,"player":"a","type":"fast","arg":null,"priority":20},{"turn":53,"player":"b","type":"fast","arg":null,"priority":20},{"turn":55,"player":"b","type":"charged","arg":"b","priority":0},{"turn":54,"player":"b","type":"fast","arg":null,"priority":-20},{"turn":53,"player":"a","type":"fast","arg":null,"priority":20},{"turn":54,"player":"a","type":"fast","arg":null,"priority":20},{"turn":57,"player":"a","type":"charged","arg":"a","priority":0}]}